examples/__init__.py
multivenv/__init__.py
multivenv/__main__.py
multivenv/_cli.py
multivenv/_compile.py
multivenv/_config.py
multivenv/_create.py
multivenv/_delete.py
multivenv/_dirutils.py
multivenv/_env.py
multivenv/_ext_packaging.py
multivenv/_ext_pip.py
multivenv/_ext_subprocess.py
multivenv/_find_reqs.py
multivenv/_info.py
multivenv/_platform.py
multivenv/_run.py
multivenv/_state.py
multivenv/_styles.py
multivenv/_sync.py
multivenv/_types.py
multivenv/exc.py
tests/__init__.py
tests/config.py
tests/conftest.py
tests/dirutils.py
tests/ext_click.py
tests/osutils.py
tests/test_cli.py
tests/test_cli_python_api.py
tests/test_compile.py
tests/test_delete.py
tests/test_ext_subprocess.py
tests/test_info.py
tests/test_run.py
tests/test_state.py
tests/test_sync.py
tests/venvutils.py
tests/fixtures/__init__.py
tests/fixtures/targets.py
tests/fixtures/temp_dir.py
tests/fixtures/venv_configs.py
tests/fixtures/venvs.py
multivenv-1.0.0a40.dist-info/LICENSE.md
multivenv-1.0.0a40.dist-info/METADATA
multivenv-1.0.0a40.dist-info/WHEEL
multivenv-1.0.0a40.dist-info/entry_points.txt
multivenv-1.0.0a40.dist-info/top_level.txt
multivenv-1.0.0a40.dist-info/RECORD
