Metadata-Version: 2.1
Name: multivenv
Version: 1.0.0a40
Summary: Python Virtualenv manager supporting multiple venvs and platforms in one project
Home-page: https://github.com/nickderobertis/multivenv
Author: Nick DeRobertis
Author-email: derobertis.nick@gmail.com
License: MIT
Project-URL: Code, https://github.com/nickderobertis/multivenv
Project-URL: Documentation, https://nickderobertis.github.io/multivenv
Classifier: Development Status :: 3 - Alpha
Classifier: Intended Audience :: Developers
Classifier: Programming Language :: Python :: 3.6
Classifier: Programming Language :: Python :: 3.7
License-File: LICENSE.md
Requires-Dist: virtualenv
Requires-Dist: pip-tools
Requires-Dist: cliconf
